sparc_cli/README.md
sparc_cli/__init__.py
sparc_cli/__main__.py
sparc_cli/__version__.py
sparc_cli/agent_utils.py
sparc_cli/calculator.py
sparc_cli/config.py
sparc_cli/env.py
sparc_cli/install.sh
sparc_cli/llm.py
sparc_cli/polaris.py
sparc_cli/prompts.py
sparc_cli/setup.py
sparc_cli/tool_configs.py
sparc_cli/.github/workflows/python-package.yml
sparc_cli/console/__init__.py
sparc_cli/console/cowboy_messages.py
sparc_cli/console/formatting.py
sparc_cli/console/output.py
sparc_cli/docs/README.md
sparc_cli/docs/advanced.md
sparc_cli/docs/architecture.md
sparc_cli/docs/eval-math.md
sparc_cli/docs/eval.md
sparc_cli/docs/usage.md
sparc_cli/examples/bug_fixer_example.sh
sparc_cli/examples/chat_example.sh
sparc_cli/examples/cowboy_mode_example.sh
sparc_cli/examples/polaris_example.py
sparc_cli/examples/research_example.sh
sparc_cli/examples/security_enhancer_example.sh
sparc_cli/examples/spec_creator_example.sh
sparc_cli/examples/webui_creator_example.sh
sparc_cli/proc/interactive.py
sparc_cli/text/__init__.py
sparc_cli/text/processing.py
sparc_cli/tools/__init__.py
sparc_cli/tools/agent.py
sparc_cli/tools/directory.py
sparc_cli/tools/expert.py
sparc_cli/tools/file_str_replace.py
sparc_cli/tools/fuzzy_find.py
sparc_cli/tools/human.py
sparc_cli/tools/list_directory.py
sparc_cli/tools/memory.py
sparc_cli/tools/polaris.py
sparc_cli/tools/programmer.py
sparc_cli/tools/read_file.py
sparc_cli/tools/research.py
sparc_cli/tools/ripgrep.py
sparc_cli/tools/scape.py
sparc_cli/tools/scrape.py
sparc_cli/tools/shell.py
sparc_cli/tools/write_file.py
sparc_cli/tools/math/README.md
sparc_cli/tools/math/__init__.py
sparc_cli/tools/math/agent.py
sparc_cli/tools/math/evaluator.py
sparc_cli/tools/math/models.py
sparc_cli/tools/math/test_agent.py
sparc_cli/tools/math/test_evaluator.py
sparc_cli/tools/math/validator.py
sparc-0.87.7.dist-info/METADATA
sparc-0.87.7.dist-info/WHEEL
sparc-0.87.7.dist-info/entry_points.txt
sparc-0.87.7.dist-info/licenses/LICENSE
sparc-0.87.7.dist-info/RECORD
