Metadata-Version: 2.4
Name: sparc
Version: 0.87.7
Summary: SPARC CLI - SPARC Framework Command Line Interface
Project-URL: Homepage, https://github.com/ai-christianson/sparc
Project-URL: Documentation, https://github.com/ai-christianson/sparc#readme
Project-URL: Repository, https://github.com/ai-christianson/sparc.git
Project-URL: Issues, https://github.com/ai-christianson/sparc/issues
Author-email: AI Christianson <ai.christianson@christianson.ai>
License: 
License-File: LICENSE
Keywords: agent,ai,development,langchain,tools
Classifier: Development Status :: 4 - Beta
Classifier: Intended Audience :: Developers
Classifier: License :: OSI Approved :: Apache Software License
Classifier: Programming Language :: Python :: 3
Classifier: Programming Language :: Python :: 3.8
Classifier: Programming Language :: Python :: 3.9
Classifier: Programming Language :: Python :: 3.10
Classifier: Topic :: Software Development :: Libraries :: Python Modules
Requires-Python: >=3.8
Requires-Dist: aider-chat>=0.69.1
Requires-Dist: fuzzywuzzy==0.18.0
Requires-Dist: gitpython>=3.1
Requires-Dist: langchain-anthropic>=0.3.1
Requires-Dist: langchain-core>=0.3.28
Requires-Dist: langchain-openai
Requires-Dist: langchain>=0.1.0
Requires-Dist: langgraph-checkpoint>=2.0.9
Requires-Dist: langgraph-sdk>=0.1.48
Requires-Dist: langgraph>=0.2.60
Requires-Dist: pathspec>=0.11.0
Requires-Dist: playwright>=1.39.0
Requires-Dist: python-levenshtein==0.23.0
Requires-Dist: rich>=13.0.0
Requires-Dist: ripgrepy>=0.1.0
Provides-Extra: dev
Requires-Dist: pytest-timeout>=2.2.0; extra == 'dev'
Requires-Dist: pytest>=7.0.0; extra == 'dev'
